voicehub
