Metadata-Version: 2.1
Name: voicehub
Version: 0.1.6
Summary: VoiceHub: A Unified Inference Interface for TTS Models
Home-page: https://github.com/kadirnar/voicehub
Author: kadirnardev
Author-email: kadir.nar@hotmail.com
License: Apache-2.0
License-File: LICENSE
Requires-Dist: transformers
Requires-Dist: snac
Requires-Dist: librosa
Requires-Dist: torchaudio
Requires-Dist: pydantic
Requires-Dist: descript-audio-codec
Requires-Dist: soundfile
Requires-Dist: inflect
Requires-Dist: pandas
Requires-Dist: pyannote.audio
